{
    "compos": [
        {
            "column_min": 26,
            "row_min": 99,
            "height": 17,
            "width": 55,
            "column_max": 81,
            "class": "text",
            "id": 0,
            "row_max": 116
        },
        {
            "column_min": 119,
            "row_min": 132,
            "height": 21,
            "width": 43,
            "column_max": 162,
            "class": "img",
            "id": 1,
            "row_max": 153
        },
        {
            "column_min": 28,
            "row_min": 173,
            "height": 44,
            "width": 106,
            "column_max": 134,
            "class": "img",
            "id": 2,
            "row_max": 217
        },
        {
            "column_min": 0,
            "row_min": 0,
            "height": 91,
            "width": 335,
            "column_max": 335,
            "class": "img",
            "id": 3,
            "row_max": 91
        },
        {
            "column_min": 0,
            "row_min": 520,
            "height": 37,
            "width": 260,
            "column_max": 260,
            "class": "img",
            "id": 4,
            "row_max": 557
        },
        {
            "column_min": 0,
            "row_min": 24,
            "height": 49,
            "width": 290,
            "column_max": 290,
            "class": "button",
            "id": 5,
            "row_max": 73
        }
    ]
}